pydelegate/__init__.py
pydelegate-0.3.0.dist-info/LICENSE
pydelegate-0.3.0.dist-info/WHEEL
pydelegate-0.3.0.dist-info/METADATA
pydelegate-0.3.0.dist-info/RECORD
