Metadata-Version: 2.1
Name: pydelegate
Version: 0.3.0
Summary: a python version delegate like C#
Home-page: https://github.com/Cologler/pydelegate-python
License: MIT
Keywords: delegate
Author: Cologler
Author-email: skyoflw@gmail.com
Requires-Python: >=3.8,<4.0
Classifier: License :: OSI Approved :: MIT License
Classifier: Programming Language :: Python :: 3
Classifier: Programming Language :: Python :: 3.10
Classifier: Programming Language :: Python :: 3.8
Classifier: Programming Language :: Python :: 3.9
